dcontainer/__init__.py
dcontainer/__main__.py
dcontainer/py.typed
dcontainer/cli/__init__.py
dcontainer/cli/generate.py
dcontainer/devcontainer/__init__.py
dcontainer/devcontainer/feature_generation/__init__.py
dcontainer/devcontainer/feature_generation/oci_feature_generator.py
dcontainer/devcontainer/feature_generation/dir_models/__init__.py
dcontainer/devcontainer/feature_generation/dir_models/src_dir.py
dcontainer/devcontainer/feature_generation/dir_models/test_dir.py
dcontainer/devcontainer/feature_generation/file_models/__init__.py
dcontainer/devcontainer/feature_generation/file_models/devcontainer_feature_json.py
dcontainer/devcontainer/feature_generation/file_models/install_sh.py
dcontainer/devcontainer/feature_generation/file_models/library_scripts_sh.py
dcontainer/devcontainer/feature_generation/file_models/readme_md.py
dcontainer/devcontainer/feature_generation/file_models/scenarios_json.py
dcontainer/devcontainer/feature_generation/file_models/test_sh.py
dcontainer/devcontainer/models/__init__.py
dcontainer/devcontainer/models/devcontainer_feature.py
dcontainer/devcontainer/models/devcontainer_feature_definition.py
dcontainer/utils/__init__.py
dcontainer/utils/settings.py
dcontainer/utils/version.py
dcontainer-1.0.12.dist-info/METADATA
dcontainer-1.0.12.dist-info/WHEEL
dcontainer-1.0.12.dist-info/entry_points.txt
dcontainer-1.0.12.dist-info/top_level.txt
dcontainer-1.0.12.dist-info/RECORD
